{
  "ts": 1781021194826,
  "results": {
    "BD": {
      "fiat": "BDT",
      "marketRate": 122.743699,
      "p2pMedian": 127.6,
      "offsetPct": 4,
      "source": "binance",
      "nAds": 10
    },
    "PK": {
      "fiat": "PKR",
      "marketRate": 278.174601,
      "p2pMedian": 289.95,
      "offsetPct": 4.2,
      "source": "binance",
      "nAds": 10
    },
    "LK": {
      "fiat": "LKR",
      "marketRate": 336.392185,
      "p2pMedian": 344.9,
      "offsetPct": 2.5,
      "source": "binance",
      "nAds": 10
    },
    "ET": {
      "fiat": "ETB",
      "marketRate": 159.315009,
      "p2pMedian": null,
      "offsetPct": null,
      "source": null,
      "nAds": 0
    },
    "GH": {
      "fiat": "GHS",
      "marketRate": 11.811194,
      "p2pMedian": 12.41,
      "offsetPct": 5.1,
      "source": "bybit",
      "nAds": 10
    },
    "CD": {
      "fiat": "CDF",
      "marketRate": 2287.743105,
      "p2pMedian": 2786.38,
      "offsetPct": 21.8,
      "source": "binance",
      "nAds": 10
    },
    "AO": {
      "fiat": "AOA",
      "marketRate": 926.01941,
      "p2pMedian": 1131.79,
      "offsetPct": 22.2,
      "source": "binance",
      "nAds": 10
    },
    "KE": {
      "fiat": "KES",
      "marketRate": 129.216109,
      "p2pMedian": 130,
      "offsetPct": 0.6,
      "source": "binance",
      "nAds": 10
    },
    "CO": {
      "fiat": "COP",
      "marketRate": 3602.817479,
      "p2pMedian": 3553.22,
      "offsetPct": -1.4,
      "source": "binance",
      "nAds": 10
    },
    "UG": {
      "fiat": "UGX",
      "marketRate": 3738.726769,
      "p2pMedian": 3801.69,
      "offsetPct": 1.7,
      "source": "binance",
      "nAds": 10
    },
    "GT": {
      "fiat": "GTQ",
      "marketRate": 7.611538,
      "p2pMedian": 7.929,
      "offsetPct": 4.2,
      "source": "binance",
      "nAds": 10
    },
    "DO": {
      "fiat": "DOP",
      "marketRate": 58.160479,
      "p2pMedian": 62.09,
      "offsetPct": 6.8,
      "source": "binance",
      "nAds": 10
    },
    "HN": {
      "fiat": "HNL",
      "marketRate": 26.593992,
      "p2pMedian": 28,
      "offsetPct": 5.3,
      "source": "binance",
      "nAds": 10
    },
    "CR": {
      "fiat": "CRC",
      "marketRate": 459.743574,
      "p2pMedian": 471.05,
      "offsetPct": 2.5,
      "source": "binance",
      "nAds": 10
    },
    "PY": {
      "fiat": "PYG",
      "marketRate": 6105.047557,
      "p2pMedian": 6175.4,
      "offsetPct": 1.2,
      "source": "binance",
      "nAds": 10
    },
    "ZM": {
      "fiat": "ZMW",
      "marketRate": 17.65058,
      "p2pMedian": 18.41,
      "offsetPct": 4.3,
      "source": "binance",
      "nAds": 10
    }
  }
}
