{
  "ts": 1784548663822,
  "results": {
    "BD": {
      "fiat": "BDT",
      "marketRate": 123.379597,
      "p2pMedian": 129.7,
      "offsetPct": 5.1,
      "source": "binance",
      "nAds": 10
    },
    "PK": {
      "fiat": "PKR",
      "marketRate": 278.166527,
      "p2pMedian": 300.13,
      "offsetPct": 7.9,
      "source": "binance",
      "nAds": 10
    },
    "LK": {
      "fiat": "LKR",
      "marketRate": 336.293417,
      "p2pMedian": 346.64,
      "offsetPct": 3.1,
      "source": "binance",
      "nAds": 10
    },
    "ET": {
      "fiat": "ETB",
      "marketRate": 160.539903,
      "p2pMedian": null,
      "offsetPct": null,
      "source": null,
      "nAds": 0
    },
    "GH": {
      "fiat": "GHS",
      "marketRate": 11.546695,
      "p2pMedian": 12.05,
      "offsetPct": 4.4,
      "source": "bybit",
      "nAds": 10
    },
    "CD": {
      "fiat": "CDF",
      "marketRate": 2300.316268,
      "p2pMedian": 2775.46,
      "offsetPct": 20.7,
      "source": "binance",
      "nAds": 10
    },
    "AO": {
      "fiat": "AOA",
      "marketRate": 920.684819,
      "p2pMedian": 1035.39,
      "offsetPct": 12.5,
      "source": "binance",
      "nAds": 10
    },
    "KE": {
      "fiat": "KES",
      "marketRate": 129.286581,
      "p2pMedian": 130,
      "offsetPct": 0.6,
      "source": "binance",
      "nAds": 10
    },
    "CO": {
      "fiat": "COP",
      "marketRate": 3248.55885,
      "p2pMedian": 3239,
      "offsetPct": -0.3,
      "source": "binance",
      "nAds": 10
    },
    "UG": {
      "fiat": "UGX",
      "marketRate": 3691.095918,
      "p2pMedian": 3790.52,
      "offsetPct": 2.7,
      "source": "binance",
      "nAds": 10
    },
    "GT": {
      "fiat": "GTQ",
      "marketRate": 7.632274,
      "p2pMedian": 7.844,
      "offsetPct": 2.8,
      "source": "binance",
      "nAds": 10
    },
    "DO": {
      "fiat": "DOP",
      "marketRate": 58.547537,
      "p2pMedian": 60,
      "offsetPct": 2.5,
      "source": "binance",
      "nAds": 10
    },
    "HN": {
      "fiat": "HNL",
      "marketRate": 26.789857,
      "p2pMedian": 27.77,
      "offsetPct": 3.7,
      "source": "binance",
      "nAds": 10
    },
    "CR": {
      "fiat": "CRC",
      "marketRate": 454.111967,
      "p2pMedian": 445.5,
      "offsetPct": -1.9,
      "source": "binance",
      "nAds": 10
    },
    "PY": {
      "fiat": "PYG",
      "marketRate": 6052.893278,
      "p2pMedian": 5987,
      "offsetPct": -1.1,
      "source": "binance",
      "nAds": 10
    },
    "ZM": {
      "fiat": "ZMW",
      "marketRate": 18.213503,
      "p2pMedian": 18.73,
      "offsetPct": 2.8,
      "source": "binance",
      "nAds": 10
    }
  }
}
