{
  "ts": 1779980632471,
  "results": {
    "BD": {
      "fiat": "BDT",
      "marketRate": 122.719189,
      "p2pMedian": 128.4,
      "offsetPct": 4.6,
      "source": "binance",
      "nAds": 10
    },
    "PK": {
      "fiat": "PKR",
      "marketRate": 278.523885,
      "p2pMedian": 287,
      "offsetPct": 3,
      "source": "binance",
      "nAds": 10
    },
    "LK": {
      "fiat": "LKR",
      "marketRate": 327.274307,
      "p2pMedian": 336.95,
      "offsetPct": 3,
      "source": "binance",
      "nAds": 10
    },
    "ET": {
      "fiat": "ETB",
      "marketRate": 157.996659,
      "p2pMedian": null,
      "offsetPct": null,
      "source": null,
      "nAds": 0
    },
    "GH": {
      "fiat": "GHS",
      "marketRate": 11.671111,
      "p2pMedian": 12.15,
      "offsetPct": 4.1,
      "source": "bybit",
      "nAds": 10
    },
    "CD": {
      "fiat": "CDF",
      "marketRate": 2264.963045,
      "p2pMedian": 2764.48,
      "offsetPct": 22.1,
      "source": "binance",
      "nAds": 10
    },
    "AO": {
      "fiat": "AOA",
      "marketRate": 927.032151,
      "p2pMedian": 1118.63,
      "offsetPct": 20.7,
      "source": "binance",
      "nAds": 10
    },
    "KE": {
      "fiat": "KES",
      "marketRate": 129.487688,
      "p2pMedian": 133,
      "offsetPct": 2.7,
      "source": "binance",
      "nAds": 10
    },
    "CO": {
      "fiat": "COP",
      "marketRate": 3670.042314,
      "p2pMedian": 3613.01,
      "offsetPct": -1.6,
      "source": "binance",
      "nAds": 10
    },
    "UG": {
      "fiat": "UGX",
      "marketRate": 3760.513745,
      "p2pMedian": 3760,
      "offsetPct": 0,
      "source": "binance",
      "nAds": 10
    },
    "GT": {
      "fiat": "GTQ",
      "marketRate": 7.624227,
      "p2pMedian": 7.948,
      "offsetPct": 4.2,
      "source": "binance",
      "nAds": 10
    },
    "DO": {
      "fiat": "DOP",
      "marketRate": 58.953457,
      "p2pMedian": 59.27,
      "offsetPct": 0.5,
      "source": "binance",
      "nAds": 10
    },
    "HN": {
      "fiat": "HNL",
      "marketRate": 26.599923,
      "p2pMedian": 27.23,
      "offsetPct": 2.4,
      "source": "binance",
      "nAds": 10
    },
    "CR": {
      "fiat": "CRC",
      "marketRate": 452.627554,
      "p2pMedian": 462,
      "offsetPct": 2.1,
      "source": "binance",
      "nAds": 10
    },
    "PY": {
      "fiat": "PYG",
      "marketRate": 6131.922851,
      "p2pMedian": 6126.61,
      "offsetPct": -0.1,
      "source": "binance",
      "nAds": 10
    },
    "ZM": {
      "fiat": "ZMW",
      "marketRate": 18.672097,
      "p2pMedian": 18.98,
      "offsetPct": 1.6,
      "source": "binance",
      "nAds": 10
    }
  }
}
